Metadata-Version: 2.4
Name: folioflex
Version: 1.5.0
Summary: A collection of portfolio tracking capabilities
Author-email: John Koestner <johnkoestner@outlook.com>
License: The MIT License (MIT)
Project-URL: homepage, https://github.com/jkoestner/folioflex
Project-URL: documentation, https://jkoestner.github.io/folioflex/
Project-URL: repository, https://github.com/jkoestner/folioflex
Requires-Python: >=3.10
License-File: LICENSE.md
Requires-Dist: ipywidgets>=8.1.5
Requires-Dist: fredapi>=0.5.2
Requires-Dist: jupyter-dash>=0.4.2
Requires-Dist: jupyterlab>=4.3.0
Requires-Dist: kaleido<0.2.0,>=0.1.0
Requires-Dist: numpy>=1.26.4
Requires-Dist: openpyxl>=3.1.5
Requires-Dist: pandas>=2.2.3
Requires-Dist: pandas-market-calendars>=4.4.1
Requires-Dist: pyxirr>=0.10.6
Requires-Dist: sqlalchemy>=2.0.36
Requires-Dist: yfinance>=0.2.51
Requires-Dist: tzlocal>=5.2
Requires-Dist: dash>=3.0.2
Requires-Dist: dash-ag-grid>=31.3.1
Requires-Dist: dash_bootstrap_components>=2.0.0
Requires-Dist: dash-core-components>=2.0.0
Requires-Dist: dash-html-components>=2.0.0
Requires-Dist: dash-renderer>=1.9.1
Requires-Dist: dash-table>=5.0.0
Requires-Dist: Flask>=3.0.3
Requires-Dist: Flask-Compress>=1.17
Requires-Dist: Flask-Login>=0.6.3
Requires-Dist: gunicorn>=23.0.0
Requires-Dist: lxml>=5.3.1
Requires-Dist: celery>=5.4.0
Requires-Dist: flower>=2.0.1
Requires-Dist: redis>=5.2.0
Requires-Dist: g4f>=0.3.3.3
Requires-Dist: hugchat>=0.4.12
Requires-Dist: openai>=1.54.3
Requires-Dist: pyautogui>=0.9.54
Requires-Dist: seleniumbase>=4.32.8
Requires-Dist: emoji>=2.14.0
Requires-Dist: gensim>=4.3.3
Requires-Dist: scikit-learn>=1.5.2
Requires-Dist: scipy<1.14
Requires-Dist: psycopg2-binary>=2.9.10
Provides-Extra: dev
Requires-Dist: black>=24.10.0; extra == "dev"
Requires-Dist: isort>=5.13.2; extra == "dev"
Requires-Dist: jupyterlab-code-formatter>=3.0.2; extra == "dev"
Requires-Dist: pytest>=8.3.3; extra == "dev"
Requires-Dist: pytest-cov>=6.0.0; extra == "dev"
Requires-Dist: ruff>=0.7.3; extra == "dev"
Requires-Dist: sphinx>=8.1; extra == "dev"
Requires-Dist: sphinx_rtd_theme>=3.0.1; extra == "dev"
Dynamic: license-file
